demos/__init__.py
demos/demo1.py
demos/demo2.py
demos/demo3.py
django_tqdm/__init__.py
django_tqdm/django_tqdm.py
tests/__init__.py
tests/test_django_tqdm.py
django_tqdm-1.3.0.dist-info/LICENSE
django_tqdm-1.3.0.dist-info/METADATA
django_tqdm-1.3.0.dist-info/WHEEL
django_tqdm-1.3.0.dist-info/top_level.txt
django_tqdm-1.3.0.dist-info/RECORD
