Metadata-Version: 2.1
Name: django-tqdm
Version: 1.3.0
Summary: Fast, Extensible Progress Meter (tqdm) For Django
Home-page: UNKNOWN
Author: Anton Samarchyan
Author-email: desecho@gmail.com
License: MIT
Project-URL: Changelog, https://github.com/desecho/django-tqdm/blob/master/CHANGELOG.md
Project-URL: Source, https://github.com/desecho/django-tqdm
Keywords: progressbar progressmeter progress bar meter rate eta console terminal time
Platform: any
Classifier: Development Status :: 5 - Production/Stable
Classifier: License :: OSI Approved :: MIT License
Classifier: Programming Language :: Python
Classifier: Programming Language :: Python :: 3
Classifier: Programming Language :: Python :: 3.7
Classifier: Programming Language :: Python :: 3.8
Classifier: Programming Language :: Python :: 3.9
Classifier: Programming Language :: Python :: 3.10
Classifier: Environment :: Console
Classifier: Topic :: Software Development :: Libraries :: Python Modules
Classifier: Topic :: Software Development :: User Interfaces
Classifier: Topic :: System :: Monitoring
Classifier: Topic :: Terminals
Classifier: Topic :: Utilities
Classifier: Intended Audience :: Developers
Classifier: Intended Audience :: System Administrators
Requires-Python: >=3.7
Requires-Dist: Django (>=2.2)
Requires-Dist: tqdm (>=4.63.0)
